bewaarbot/__init__.py
bewaarbot/__main__.py
bewaarbot/cli.py
bewaarbot/py.typed
bewaarbot-0.1.3.dist-info/entry_points.txt
bewaarbot-0.1.3.dist-info/LICENSE
bewaarbot-0.1.3.dist-info/WHEEL
bewaarbot-0.1.3.dist-info/METADATA
bewaarbot-0.1.3.dist-info/RECORD
