Metadata-Version: 2.1
Name: bewaarbot
Version: 0.1.3
Summary: Awesome `bewaarbot` is a Python cli/package created with https://github.com/TezRomacH/python-package-template
Home-page: https://github.com/theanarchox/bewaarbot
License: MIT
Author: TheAnarchoX
Author-email: theanarchox@riseup.net
Requires-Python: >=3.8,<4.0
Classifier: Development Status :: 3 - Alpha
Classifier: Intended Audience :: Developers
Classifier: License :: OSI Approved :: MIT License
Classifier: Operating System :: OS Independent
Classifier: Programming Language :: Python :: 3
Classifier: Programming Language :: Python :: 3.8
Classifier: Programming Language :: Python :: 3.9
Classifier: Topic :: Software Development :: Libraries :: Python Modules
Requires-Dist: importlib_metadata (>=3.6.0,<4.0.0); python_version >= "3.8" and python_version < "4.0"
Requires-Dist: rich (>=9.8.2,<10.0.0)
Requires-Dist: typer[all] (>=0.3.2,<0.4.0)
Project-URL: Repository, https://github.com/theanarchox/bewaarbot
